mrinversion/__init__.py
mrinversion/utils.py
mrinversion/kernel/__init__.py
mrinversion/kernel/base.py
mrinversion/kernel/csa_aniso.py
mrinversion/kernel/nmr.py
mrinversion/kernel/quad_aniso.py
mrinversion/kernel/relaxation.py
mrinversion/kernel/utils.py
mrinversion/linear_model/__init__.py
mrinversion/linear_model/_base_l1l2.py
mrinversion/linear_model/fista_lasso.py
mrinversion/linear_model/linear_inversion.py
mrinversion/linear_model/smooth_lasso.py
mrinversion/linear_model/sparse_rigid_fusion.py
mrinversion/linear_model/tsvd_compression.py
mrinversion/linear_model/fista/__init__.py
mrinversion-0.3.1.dist-info/LICENSE
mrinversion-0.3.1.dist-info/METADATA
mrinversion-0.3.1.dist-info/WHEEL
mrinversion-0.3.1.dist-info/top_level.txt
mrinversion-0.3.1.dist-info/RECORD
