Metadata-Version: 2.1
Name: mrinversion
Version: 0.3.1
Summary: Python based statistical learning of NMR tensor and relaxation parameters distribution.
Home-page: https://github.com/DeepanshS/mrinversion/
Author: Deepansh J. Srivastava
Author-email: deepansh2012@gmail.com
License: BSD-3-Clause
Classifier: Intended Audience :: Science/Research
Classifier: Intended Audience :: Developers
Classifier: Operating System :: OS Independent
Classifier: Development Status :: 4 - Beta
Classifier: License :: OSI Approved :: BSD License
Classifier: Programming Language :: Python :: 3
Classifier: Programming Language :: Python :: 3.10
Classifier: Programming Language :: Python :: 3.11
Classifier: Programming Language :: Python :: 3.12
Classifier: Programming Language :: Python :: 3.13
Classifier: Topic :: Scientific/Engineering
Classifier: Topic :: Education
Classifier: Topic :: Scientific/Engineering :: Chemistry
Classifier: Topic :: Scientific/Engineering :: Physics
Requires-Python: >=3.10
License-File: LICENSE
Requires-Dist: numpy >=2.0
Requires-Dist: setuptools >=27.3
Requires-Dist: csdmpy >=0.7
Requires-Dist: mrsimulator >=1.0.0
Requires-Dist: scikit-learn >=1.5.2
Requires-Dist: numba >=0.61.2
Provides-Extra: matplotlib
Requires-Dist: matplotlib >=3.0 ; extra == 'matplotlib'
